tsds/__init__.py
tsds/clustering.py
tsds/disease_progression.py
tsds/explain.py
tsds/nmf.py
tsds/predict.py
tsds/tsds.py
tsds-0.0.4.dist-info/LICENSE
tsds-0.0.4.dist-info/METADATA
tsds-0.0.4.dist-info/WHEEL
tsds-0.0.4.dist-info/top_level.txt
tsds-0.0.4.dist-info/RECORD
