Metadata-Version: 2.1
Name: tsds
Version: 0.0.4
Summary: Python package for my library tsds.
Home-page: https://github.com/jakobudovic/tsds
Download-URL: https://github.com/jakobudovic/tsds/archive/0.0.4.tar.gz
Author: J.Udovic
Author-email: jakobudovic2@gmail.com
Classifier: Programming Language :: Python :: 3
Classifier: License :: OSI Approved :: GNU Affero General Public License v3
Classifier: Operating System :: OS Independent
Requires-Python: >=3
License-File: LICENSE
Requires-Dist: matplotlib
Requires-Dist: numpy
Requires-Dist: pandas
Requires-Dist: sklearn
Requires-Dist: shap
Requires-Dist: nltk
